VideoEmotionRecognition/__init__.py
VideoEmotionRecognition/viemr.py
VideoEmotionRecognition-0.2.91.dist-info/LICENSE
VideoEmotionRecognition-0.2.91.dist-info/METADATA
VideoEmotionRecognition-0.2.91.dist-info/WHEEL
VideoEmotionRecognition-0.2.91.dist-info/top_level.txt
VideoEmotionRecognition-0.2.91.dist-info/RECORD
