Metadata-Version: 2.1
Name: VideoEmotionRecognition
Version: 0.2.91
Summary: This package receives an mp4 file classfying it according to its emotions and generating a heat map
Author-email: Artur Lima <vligmart@gmail.com>
Project-URL: Homepage, https://github.com/Deflyer/Multimodal-Emotion-Recognition-from-Videos
Project-URL: Example, https://colab.research.google.com/drive/1UqzA6bDgtZWGji652a0UjT7ZtDh3Xyi5?authuser=1#scrollTo=CKL-Mm9D18BB
Classifier: Programming Language :: Python :: 3
Classifier: License :: OSI Approved :: MIT License
Classifier: Operating System :: OS Independent
Requires-Python: >=3.7
License-File: LICENSE
